mcp_server_youtube_info/__init__.py
mcp_server_youtube_info/__main__.py
mcp_server_youtube_info/server.py
mcp_server_youtube_info/util.py
mcp_server_youtube_info-0.1.8.dist-info/METADATA
mcp_server_youtube_info-0.1.8.dist-info/WHEEL
mcp_server_youtube_info-0.1.8.dist-info/entry_points.txt
mcp_server_youtube_info-0.1.8.dist-info/RECORD
