Metadata-Version: 2.4
Name: mcp-server-youtube-info
Version: 0.1.8
Summary: A YouTube information retrieval server implementation for Model Context Protocol (MCP)
Author-email: yareyaredesuyo <yareyaredesuyo@gmail.com>
License-Expression: MIT
Keywords: automation,llm,mcp,model-context-protocol,youtube
Classifier: Development Status :: 4 - Beta
Classifier: Intended Audience :: Developers
Classifier: License :: OSI Approved :: MIT License
Classifier: Programming Language :: Python :: 3
Classifier: Programming Language :: Python :: 3.10
Classifier: Topic :: Software Development :: Libraries :: Python Modules
Requires-Python: >=3.10
Requires-Dist: argparse>=1.4.0
Requires-Dist: fastmcp>=2.5.2
Requires-Dist: httpx>=0.28.1
Requires-Dist: pillow>=11.2.1
Requires-Dist: yt-dlp>=2025.5.22
